LICENSE
README.md
setup.cfg
setup.py
src/ubicoders_vrobots/__init__.py
src/ubicoders_vrobots.egg-info/PKG-INFO
src/ubicoders_vrobots.egg-info/SOURCES.txt
src/ubicoders_vrobots.egg-info/dependency_links.txt
src/ubicoders_vrobots.egg-info/requires.txt
src/ubicoders_vrobots.egg-info/top_level.txt
src/ubicoders_vrobots/vrobots_bridge/__init__.py
src/ubicoders_vrobots/vrobots_bridge/vr_main_srv.py
src/ubicoders_vrobots/vrobots_bridge/vr_rest_srv.py
src/ubicoders_vrobots/vrobots_bridge/vr_stopper.py
src/ubicoders_vrobots/vrobots_bridge/vr_ws_srv.py
src/ubicoders_vrobots/vrobots_clients/__init__.py
src/ubicoders_vrobots/vrobots_clients/vr_client.py
src/ubicoders_vrobots/vrobots_clients/vr_client_utils.py
src/ubicoders_vrobots/vrobots_clients/vr_service_omrover.py
src/ubicoders_vrobots/vrobots_clients/vr_service_utils.py
src/ubicoders_vrobots/vrobots_data/__init__.py
src/ubicoders_vrobots/vrobots_data/vrobots_data_reader.py
src/ubicoders_vrobots/vrobots_data/vrobots_data_writer.py
src/ubicoders_vrobots/vrobots_graph_tools/__init__.py
src/ubicoders_vrobots/vrobots_graph_tools/data_viz_matplotlib.py
src/ubicoders_vrobots/vrobots_graph_tools/data_viz_pyqt.py
src/ubicoders_vrobots/vrobots_graph_tools/data_viz_web.py
src/ubicoders_vrobots/vrobots_graph_tools/graph_srv_matplotlib.py
src/ubicoders_vrobots/vrobots_graph_tools/graph_srv_plotly.py
src/ubicoders_vrobots/vrobots_graph_tools/graph_srv_pyqt.py
src/ubicoders_vrobots/vrobots_graph_tools/graph_tool_client.py
src/ubicoders_vrobots/vrobots_graph_tools/graph_udp_server.py
src/ubicoders_vrobots/vrobots_graph_tools/main_graph_runner.py
src/ubicoders_vrobots/vrobots_msgs/VROBOTS_CMDS.py
src/ubicoders_vrobots/vrobots_msgs/__init__.py
src/ubicoders_vrobots/vrobots_msgs/clear.py
src/ubicoders_vrobots/vrobots_msgs/fbpy_utils.py
src/ubicoders_vrobots/vrobots_msgs/gen_all.py
src/ubicoders_vrobots/vrobots_msgs/gen_cmds_dotnet.py
src/ubicoders_vrobots/vrobots_msgs/gen_cmds_python.py
src/ubicoders_vrobots/vrobots_msgs/gen_cmds_ts.py
src/ubicoders_vrobots/vrobots_msgs/gen_fb_srv_defs.py
src/ubicoders_vrobots/vrobots_msgs/gen_fid_python.py
src/ubicoders_vrobots/vrobots_msgs/gen_flatbuffers.py
src/ubicoders_vrobots/vrobots_msgs/gen_states_enum_dotnet.py
