Metadata-Version: 2.1
Name: ubicoders-vrobots
Version: 2.0.29
Home-page: https://github.com/ubicoders0/vrobots
Author: Elliot Lee
Author-email: info@airnh.ca
License: GPLv3
Keywords: ubicoders virtual robots
License-File: LICENSE
Requires-Dist: websockets
Requires-Dist: websocket-client
Requires-Dist: numpy
Requires-Dist: flatbuffers==23.5.26
Requires-Dist: fastapi
Requires-Dist: uvicorn
Requires-Dist: asyncio
Requires-Dist: requests
Requires-Dist: psutil
Requires-Dist: dash
Requires-Dist: plotly
Requires-Dist: colorama
Requires-Dist: matplotlib
Requires-Dist: pyqt5
Requires-Dist: pyqtgraph
Requires-Dist: pandas
Requires-Dist: scipy
Requires-Dist: ipython
Requires-Dist: ipykernel
Requires-Dist: jupyterlab
